<form version="1.1" theme="dark">
  <label>sc4snmp</label>
  <fieldset submitButton="false" autoRun="true"></fieldset>
  <row>
    <panel>
      <title>SNMP polling status</title>
      <input type="dropdown" token="poll_status_host" searchWhenChanged="true">
        <label>SNMP device</label>
        <choice value="*">all</choice>
        <default>*</default>
        <initialValue>*</initialValue>
        <fieldForLabel>ip</fieldForLabel>
        <fieldForValue>ip</fieldForValue>
        <search>
          <query>index=* sourcetype="*:container:splunk-connect-for-snmp-*" "Scheduler: Sending due task sc4snmp;*;*;poll" | rex field=_raw "Sending due task sc4snmp;(?&lt;ip&gt;.+);(?&lt;num&gt;\d+);poll" | stats count by ip</query>
          <earliest>-24h@h</earliest>
          <latest>now</latest>
        </search>
      </input>
      <chart>
        <title>In case of unsuccessful polling status, please copy spl query from this chart and find failed tasks. Explanation of error log messages you can find at the https://splunk.github.io/splunk-connect-for-snmp/main/bestpractices/</title>
        <search>
          <query>index=* sourcetype="*:container:splunk-connect-for-snmp-*" splunk_connect_for_snmp.snmp.tasks.poll $poll_status_host$ | rex field=_raw "Task splunk_connect_for_snmp.*\[*\] (?&lt;status&gt;\w+)" | where status != "received" | timechart count by status</query>
          <earliest>-24h@h</earliest>
          <latest>now</latest>
          <refresh>5m</refresh>
          <refreshType>delay</refreshType>
        </search>
        <option name="charting.axisTitleX.visibility">visible</option>
        <option name="charting.axisTitleY.visibility">visible</option>
        <option name="charting.axisTitleY2.visibility">visible</option>
        <option name="charting.chart">line</option>
        <option name="charting.chart.nullValueMode">connect</option>
        <option name="charting.drilldown">all</option>
        <option name="charting.legend.placement">right</option>
        <option name="height">331</option>
        <option name="refresh.display">progressbar</option>
        <option name="trellis.enabled">0</option>
        <drilldown>
          <link target="_blank">search?q=index%3D*%20sourcetype%3D%22*%3Acontainer%3Asplunk-connect-for-snmp-*%22%20splunk_connect_for_snmp.snmp.tasks.poll%20$poll_status_host$%20%7C%20rex%20field%3D_raw%20%22Task%20splunk_connect_for_snmp.*%5C%5B*%5C%5D%20(%3F%3Cstatus%3E%5Cw%2B)%22%20%7C%20where%20status%20!%3D%20%22received%22&amp;earliest=-24h@h&amp;latest=now</link>
        </drilldown>
      </chart>
    </panel>
    <panel>
      <title>SNMP schedule of polling tasks</title>
      <input type="dropdown" token="poll_host" searchWhenChanged="true">
        <label>SNMP device</label>
        <choice value="*">all</choice>
        <default>*</default>
        <initialValue>*</initialValue>
        <fieldForLabel>ip</fieldForLabel>
        <fieldForValue>ip</fieldForValue>
        <search>
          <query>index=* sourcetype="*:container:splunk-connect-for-snmp-*" "Scheduler: Sending due task sc4snmp;*;*;poll" | rex field=_raw "Sending due task sc4snmp;(?&lt;ip&gt;.+);(?&lt;num&gt;\d+);poll" | stats count by ip</query>
          <earliest>-24h@h</earliest>
          <latest>now</latest>
        </search>
      </input>
      <chart>
        <title>Using this chart you can understand when SC4SNMP scheduled polling for your SNMP device last time. The process works if it runs regularly.</title>
        <search>
          <query>index=* sourcetype="*:container:splunk-connect-for-snmp-*" Scheduler: Sending due task sc4snmp;$poll_host$;*poll | timechart count</query>
          <earliest>-24h@h</earliest>
          <latest>now</latest>
          <refresh>5m</refresh>
          <refreshType>delay</refreshType>
        </search>
        <option name="charting.chart">line</option>
        <option name="charting.drilldown">all</option>
        <option name="height">331</option>
        <option name="refresh.display">progressbar</option>
        <drilldown>
          <link target="_blank">search?q=index%3D*%20sourcetype%3D%22*%3Acontainer%3Asplunk-connect-for-snmp-*%22%20Scheduler%3A%20Sending%20due%20task%20sc4snmp%3B$poll_host$%3B*poll&amp;earliest=-24h@h&amp;latest=now</link>
        </drilldown>
      </chart>
    </panel>
  </row>
  <row>
    <panel>
      <title>SNMP walk status</title>
      <input type="dropdown" token="walk_status_host">
        <label>SNMP device</label>
        <choice value="*">all</choice>
        <default>*</default>
        <initialValue>*</initialValue>
        <fieldForLabel>ip</fieldForLabel>
        <fieldForValue>ip</fieldForValue>
        <search>
          <query>index=* sourcetype="*:container:splunk-connect-for-snmp-*" "Scheduler: Sending due task sc4snmp;*;walk" | rex field=_raw "Sending due task sc4snmp;(?&lt;ip&gt;.+);walk" | stats count by ip</query>
          <earliest>-24h@h</earliest>
          <latest>now</latest>
        </search>
      </input>
      <chart>
        <title>In case of unsuccessful walk status, please copy spl query from this chart and find failed tasks. Explanation of error log messages you can find at the https://splunk.github.io/splunk-connect-for-snmp/main/bestpractices/</title>
        <search>
          <query>index=* sourcetype="*:container:splunk-connect-for-snmp-*" splunk_connect_for_snmp.snmp.tasks.walk $walk_status_host$ | rex field=_raw "Task splunk_connect_for_snmp.*\[*\] (?&lt;status&gt;\w+)" | where status != "received" | timechart count by status</query>
          <earliest>-24h@h</earliest>
          <latest>now</latest>
          <refresh>5m</refresh>
          <refreshType>delay</refreshType>
        </search>
        <option name="charting.chart">line</option>
        <option name="charting.drilldown">all</option>
        <option name="height">327</option>
        <option name="refresh.display">progressbar</option>
        <drilldown>
          <link target="_blank">search?q=index%3D*%20sourcetype%3D%22kube%3Acontainer%3Asplunk-connect-for-snmp-*%22%20splunk_connect_for_snmp.snmp.tasks.walk%20$walk_status_host$%20%7C%20rex%20field%3D_raw%20%22Task%20splunk_connect_for_snmp.*%5C%5B*%5C%5D%20(%3F%3Cstatus%3E%5Cw%2B)%22%20%7C%20where%20status%20!%3D%20%22received%22&amp;earliest=-24h@h&amp;latest=now</link>
        </drilldown>
      </chart>
    </panel>
    <panel>
      <title>SNMP schedule for walk tasks</title>
      <input type="dropdown" token="walk_host">
        <label>SNMP device</label>
        <choice value="*">all</choice>
        <default>*</default>
        <initialValue>*</initialValue>
        <fieldForLabel>ip</fieldForLabel>
        <fieldForValue>ip</fieldForValue>
        <search>
          <query>index=* sourcetype="*:container:splunk-connect-for-snmp-*" "Scheduler: Sending due task sc4snmp;*;walk" | rex field=_raw "Sending due task sc4snmp;(?&lt;ip&gt;.+);walk" | stats count by ip</query>
          <earliest>-24h@h</earliest>
          <latest>now</latest>
        </search>
      </input>
      <chart>
        <title>Using this chart you can understand when SC4SNMP scheduled walk for your SNMP device last time. The process works if it runs regularly.</title>
        <search>
          <query>index=* sourcetype="*:container:splunk-connect-for-snmp-*" Scheduler: Sending due task sc4snmp;$walk_host$;walk | timechart count</query>
          <earliest>-24h@h</earliest>
          <latest>now</latest>
          <refresh>5m</refresh>
          <refreshType>delay</refreshType>
        </search>
        <option name="charting.chart">line</option>
        <option name="charting.drilldown">all</option>
        <option name="height">324</option>
        <option name="refresh.display">progressbar</option>
        <drilldown>
          <link target="_blank">search?q=index%3D*%20sourcetype%3D%22*%3Acontainer%3Asplunk-connect-for-snmp-*%22%20Scheduler%3A%20Sending%20due%20task%20sc4snmp%3B$walk_host$%3Bwalk&amp;earliest=-24h@h&amp;latest=now</link>
        </drilldown>
      </chart>
    </panel>
  </row>
  <row>
    <panel>
      <title>SNMP trap status</title>
      <chart>
        <title>In case of unsuccessful trap status, please copy spl query from this chart and find failed tasks. Explanation of error log messages you can find at the https://splunk.github.io/splunk-connect-for-snmp/main/bestpractices/</title>
        <search>
          <query>index=* sourcetype="*:container:splunk-connect-for-snmp-*" splunk_connect_for_snmp.snmp.tasks.trap | rex field=_raw "Task splunk_connect_for_snmp.*\[*\] (?&lt;status&gt;\w+)" | where status != "received" | timechart count by status</query>
          <earliest>-24h@h</earliest>
          <latest>now</latest>
          <refresh>5m</refresh>
          <refreshType>delay</refreshType>
        </search>
        <option name="charting.chart">line</option>
        <option name="charting.drilldown">all</option>
        <option name="height">332</option>
        <option name="refresh.display">progressbar</option>
        <drilldown>
          <link target="_blank">search?q=index%3D*%20sourcetype%3D%22*%3Acontainer%3Asplunk-connect-for-snmp-*%22%20splunk_connect_for_snmp.snmp.tasks.trap%20%7C%20rex%20field%3D_raw%20%22Task%20splunk_connect_for_snmp.*%5C%5B*%5C%5D%20(%3F%3Cstatus%3E%5Cw%2B)%22%20%7C%20where%20status%20!%3D%20%22received%22&amp;earliest=-24h@h&amp;latest=now</link>
        </drilldown>
      </chart>
    </panel>
    <panel>
      <title>SNMP trap authorisation</title>
      <chart>
        <title>If it's not succeeded it means that you have SNMP authorisation problem.</title>
        <search>
          <query>index=* "ERROR Security Model failure for device" OR "splunk_connect_for_snmp.snmp.tasks.trap\[*\] succeeded" | eval status=if(searchmatch("succeeded"), "succeeded", "failed") | timechart count by status</query>
          <earliest>-24h@h</earliest>
          <latest>now</latest>
          <refresh>5m</refresh>
          <refreshType>delay</refreshType>
        </search>
        <option name="charting.chart">line</option>
        <option name="charting.drilldown">all</option>
        <option name="height">329</option>
        <option name="refresh.display">progressbar</option>
        <drilldown>
          <link target="_blank">search?q=index%3D*%20%22ERROR%20Security%20Model%20failure%20for%20device%22&amp;earliest=-24h@h&amp;latest=now</link>
        </drilldown>
      </chart>
    </panel>
  </row>
  <row>
    <panel>
      <title>SNMP send to Splunk status</title>
      <chart>
        <title>In case of unsuccessful enrich status, please copy spl query from this chart and find failed tasks. Explanation of error log messages you can find at the https://splunk.github.io/splunk-connect-for-snmp/main/bestpractices/</title>
        <search>
          <query>index=* sourcetype="*:container:splunk-connect-for-snmp-*" splunk_connect_for_snmp.splunk.tasks.send | rex field=_raw "Task splunk_connect_for_snmp.*\[*\] (?&lt;status&gt;\w+)" | where status != "received" | timechart count by status</query>
          <earliest>-24h@h</earliest>
          <latest>now</latest>
          <refresh>5m</refresh>
          <refreshType>delay</refreshType>
        </search>
        <option name="charting.chart">line</option>
        <option name="charting.drilldown">none</option>
        <option name="refresh.display">progressbar</option>
      </chart>
    </panel>
    <panel>
      <title>SNMP enrich task status</title>
      <chart>
        <title>In case of unsuccessful enrich status, please copy spl query from this chart and find failed tasks. Explanation of error log messages you can find at the https://splunk.github.io/splunk-connect-for-snmp/main/bestpractices/</title>
        <search>
          <query>index=* sourcetype="*:container:splunk-connect-for-snmp-*" splunk_connect_for_snmp.enrich.tasks.enrich | rex field=_raw "Task splunk_connect_for_snmp.*\[*\] (?&lt;status&gt;\w+)" | where status != "received" | timechart count by status</query>
          <earliest>-24h@h</earliest>
          <latest>now</latest>
          <refresh>5m</refresh>
          <refreshType>delay</refreshType>
        </search>
        <option name="charting.chart">line</option>
        <option name="charting.drilldown">none</option>
        <option name="refresh.display">progressbar</option>
      </chart>
    </panel>
    <panel>
      <title>SNMP prepare task status</title>
      <chart>
        <title>In case of unsuccessful enrich status, please copy spl query from this chart and find failed tasks. Explanation of error log messages you can find at the https://splunk.github.io/splunk-connect-for-snmp/main/bestpractices/</title>
        <search>
          <query>index=* sourcetype="*:container:splunk-connect-for-snmp-*" splunk_connect_for_snmp.splunk.tasks.prepare | rex field=_raw "Task splunk_connect_for_snmp.*\[*\] (?&lt;status&gt;\w+)" | where status != "received" | timechart count by status</query>
          <earliest>-24h@h</earliest>
          <latest>now</latest>
          <refresh>5m</refresh>
          <refreshType>delay</refreshType>
        </search>
        <option name="charting.chart">line</option>
        <option name="charting.drilldown">none</option>
        <option name="refresh.display">progressbar</option>
      </chart>
    </panel>
    <panel>
      <title>SNMP inventory poller task status</title>
      <chart>
        <title>In case of unsuccessful enrich status, please copy spl query from this chart and find failed tasks. Explanation of error log messages you can find at the https://splunk.github.io/splunk-connect-for-snmp/main/bestpractices/</title>
        <search>
          <query>index=* sourcetype="*:container:splunk-connect-for-snmp-*" splunk_connect_for_snmp.inventory.tasks.inventory_setup_poller | rex field=_raw "Task splunk_connect_for_snmp.*\[*\] (?&lt;status&gt;\w+)" | where status != "received" | timechart count by status</query>
          <earliest>-24h@h</earliest>
          <latest>now</latest>
          <refresh>5m</refresh>
          <refreshType>delay</refreshType>
        </search>
        <option name="charting.chart">line</option>
        <option name="charting.drilldown">none</option>
        <option name="refresh.display">progressbar</option>
      </chart>
    </panel>
  </row>
</form>